r6stats/__init__.py
r6stats/exceptions.py
r6stats/operators.py
r6stats/platforms.py
r6stats/result.py
r6stats/seasons.py
r6stats/stats.py
r6stats.py-1.0.1.dist-info/METADATA
r6stats.py-1.0.1.dist-info/WHEEL
r6stats.py-1.0.1.dist-info/top_level.txt
r6stats.py-1.0.1.dist-info/RECORD
